baresquare_core_py/__init__.py
baresquare_core_py/exceptions.py
baresquare_core_py/logger.py
baresquare_core_py/middleware/__init__.py
baresquare_core_py/middleware/compression.py
baresquare_core_py/middleware/cors.py
baresquare_core_py/middleware/request_info.py
baresquare_core_py-0.1.16.dist-info/METADATA
baresquare_core_py-0.1.16.dist-info/WHEEL
baresquare_core_py-0.1.16.dist-info/RECORD
