Metadata-Version: 2.4
Name: baresquare-core-py
Version: 0.1.16
Summary: Baresquare's core Python utilities
License-Expression: MIT
Requires-Python: >=3.12
Requires-Dist: fastapi>=0.115.12
Provides-Extra: linting
Requires-Dist: ruff==0.11.9; extra == 'linting'
Provides-Extra: publishing
Provides-Extra: testing
Requires-Dist: pytest==8.3.5; extra == 'testing'
